mindterm/__init__.py
mindterm/client.py
mindterm/config.py
mindterm/main.py
mindterm/ui.py
mindterm-0.3.0.dist-info/METADATA
mindterm-0.3.0.dist-info/WHEEL
mindterm-0.3.0.dist-info/entry_points.txt
mindterm-0.3.0.dist-info/licenses/LICENSE
mindterm-0.3.0.dist-info/RECORD
