Metadata-Version: 2.4
Name: mindterm
Version: 0.3.0
Summary: Intelligent terminal like thinking.
Author-email: wokspc <wokspc@gmail.com>
License-File: LICENSE
Requires-Python: >=3.11
Requires-Dist: loguru>=0.7.3
Requires-Dist: openai>=1.99.1
Requires-Dist: prompt-toolkit>=3.0.51
Requires-Dist: rich>=14.1.0
